pytarski/Boole.py
pytarski/TarskisWorld.py
pytarski/__init__.py
pytarski-0.0.7.dist-info/METADATA
pytarski-0.0.7.dist-info/WHEEL
pytarski-0.0.7.dist-info/top_level.txt
pytarski-0.0.7.dist-info/RECORD
