Metadata-Version: 2.1
Name: pytarski
Version: 0.0.7
Summary: Tarski's World for python
Author: Walt Jacob
Author-email: jacobw56@gmail.com
Keywords: python,pytarski
Classifier: Development Status :: 3 - Alpha
Classifier: Environment :: Console
Classifier: Intended Audience :: Education
Classifier: Programming Language :: Python :: 2
Classifier: Programming Language :: Python :: 3
Classifier: Operating System :: MacOS :: MacOS X
Classifier: Operating System :: Microsoft :: Windows
Classifier: Operating System :: POSIX :: Linux
